hatch_frozen/__init__.py
hatch_frozen/hooks.py
hatch_frozen/plugin.py
hatch_frozen-0.1.1.dist-info/METADATA
hatch_frozen-0.1.1.dist-info/WHEEL
hatch_frozen-0.1.1.dist-info/entry_points.txt
hatch_frozen-0.1.1.dist-info/licenses/LICENSE
hatch_frozen-0.1.1.dist-info/RECORD
