Metadata-Version: 2.4
Name: hatch-frozen
Version: 0.1.1
Summary: A build hook plugin for Hatch to freeze the depedency tree for repeatable builds
License:                                  Apache License
License-File: LICENSE
Classifier: Framework :: Hatch
Requires-Python: >=3.9
Requires-Dist: hatchling>=1.6.0
